{
        "experiment": {
            "config": {
                "save_location": "./",
                "save_frequency": 1,
                "bootstrap_size": 1
            }
        },
        "system": {
            "path": "examples.lenia.systems.LeniaCPPN.LeniaCPPN",
            "config": {
                "SX": 256,
                "SY": 256,
                "final_step": 30,
                "scale_init_state": 1,
                "cppn_n_passes":2
            }
        },
        "explorer": {
            "path": "adtool.explorers.IMGEPExplorer.IMGEPExplorer",
            "config": {
                "mutator": "specific",
                "equil_time": 1,
                "behavior_map": "examples.lenia.maps.LeniaStatistics.LeniaStatistics",
                "parameter_map": "examples.lenia.maps.LeniaCPPNParameterMap.LeniaParameterMap",
                "mutator_config": {},
                "behavior_map_config": {},
                "parameter_map_config": {
                    "init_state_dim": [10, 10],
                    "neat_config_path": "adtool/maps/cppn/config.cfg"
                }
            }
        },
        "input_wrappers": [],
        "output_representations": [],
        "logger_handlers":[],
        "callbacks": {
        "on_discovery":[
        {"path":"adtool.callbacks.on_discovery_callbacks.save_discovery_on_disk.SaveDiscoveryOnDisk",
        "config": {}
        }
        ]
        
    }
    
    }
